blind_files/__init__.py
blind_files/aho_corasick_path_generator.py
blind_files/blind_files.py
blind_files/cli.py
blind_files/data/nounlist.txt
blind_files/delimiter_path_generator.py
blind_files/identifier_mapper.py
blind_files-0.2.6.dist-info/entry_points.txt
blind_files-0.2.6.dist-info/LICENSE
blind_files-0.2.6.dist-info/WHEEL
blind_files-0.2.6.dist-info/METADATA
blind_files-0.2.6.dist-info/RECORD
