Metadata-Version: 2.1
Name: blind-files
Version: 0.2.6
Summary: Relabel files in order to work on them blind
License: MIT
Author: Pokey Rule
Author-email: 755842+pokey@users.noreply.github.com
Requires-Python: >=3.7,<4.0
Classifier: License :: OSI Approved :: MIT License
Classifier: Programming Language :: Python :: 3
Classifier: Programming Language :: Python :: 3.10
Classifier: Programming Language :: Python :: 3.7
Classifier: Programming Language :: Python :: 3.8
Classifier: Programming Language :: Python :: 3.9
Requires-Dist: click (>=8.1.2,<9.0.0)
Requires-Dist: pyahocorasick (>=1.4.4,<2.0.0)
